LICENSE
README.md
docs/architecture.md
docs/configuration.md
docs/extensibility.md
docs/getting_started.md
docs/upgrade.md
network_importer/__init__.py
network_importer/adapters/base.py
network_importer/adapters/nautobot_api/adapter.py
network_importer/adapters/nautobot_api/exceptions.py
network_importer/adapters/nautobot_api/inventory.py
network_importer/adapters/nautobot_api/models.py
network_importer/adapters/nautobot_api/settings.py
network_importer/adapters/nautobot_api/tasks.py
network_importer/adapters/netbox_api/adapter.py
network_importer/adapters/netbox_api/exceptions.py
network_importer/adapters/netbox_api/inventory.py
network_importer/adapters/netbox_api/models.py
network_importer/adapters/netbox_api/settings.py
network_importer/adapters/netbox_api/tasks.py
network_importer/adapters/network_importer/adapter.py
network_importer/adapters/network_importer/exceptions.py
network_importer/cli.py
network_importer/config.py
network_importer/diff.py
network_importer/drivers/__init__.py
network_importer/drivers/arista_eos.py
network_importer/drivers/cisco_default.py
network_importer/drivers/converters.py
network_importer/drivers/default.py
network_importer/drivers/juniper_junos.py
network_importer/exceptions.py
network_importer/inventory.py
network_importer/main.py
network_importer/models.py
network_importer/performance.py
network_importer/processors/__init__.py
network_importer/processors/get_config.py
network_importer/processors/get_neighbors.py
network_importer/processors/get_vlans.py
network_importer/tasks.py
network_importer/templates/hostvars.j2
network_importer/utils.py
network_importer-3.1.0.dist-info/entry_points.txt
network_importer-3.1.0.dist-info/LICENSE
network_importer-3.1.0.dist-info/WHEEL
network_importer-3.1.0.dist-info/METADATA
network_importer-3.1.0.dist-info/RECORD
