Metadata-Version: 2.1
Name: network-importer
Version: 3.1.0
Summary: Network Importer tool to import an existing network into a Database / Source Of Truth
Home-page: https://github.com/networktocode/network-importer
License: Apache-2.0
Keywords: network,source-of-truth,netbox,diffsync
Author: Network to Code, LLC
Author-email: opensource@networktocode.com
Requires-Python: >=3.8.0,<4.0.0
Classifier: License :: OSI Approved :: Apache Software License
Classifier: Programming Language :: Python :: 3
Classifier: Programming Language :: Python :: 3.10
Classifier: Programming Language :: Python :: 3.8
Classifier: Programming Language :: Python :: 3.9
Requires-Dist: click (>=7.1,<9.0)
Requires-Dist: diffsync (>=1.2,<2.0)
Requires-Dist: genie (>=22.7,<23.0)
Requires-Dist: netmiko (>=3.3,<4.0)
Requires-Dist: nornir (>=3.0,<4.0)
Requires-Dist: nornir-napalm (>=0.1.2,<0.2.0)
Requires-Dist: nornir-netmiko (>=0.1.1,<0.2.0)
Requires-Dist: nornir-utils (>=0.1.2,<0.2.0)
Requires-Dist: ntc-templates (>=2.0,<3.0)
Requires-Dist: pyats (>=22.7,<23.0)
Requires-Dist: pybatfish (==2021.2.26.830)
Requires-Dist: pydantic (>=1.6,<2.0)
Requires-Dist: pynautobot (>=1.0.2,<2.0.0)
Requires-Dist: pynetbox (>=5.0,<6.0)
Requires-Dist: rich (>=9.2,<10.0)
Requires-Dist: structlog (>=20.1.0,<21.0.0)
Requires-Dist: termcolor (>=1.1,<2.0)
Requires-Dist: toml (>=0.10,<0.11)
Project-URL: Repository, https://github.com/networktocode/network-importer
